cud/__init__.py
cud/cud.py
cud-0.0.2.dist-info/LICENSE.txt
cud-0.0.2.dist-info/METADATA
cud-0.0.2.dist-info/WHEEL
cud-0.0.2.dist-info/top_level.txt
cud-0.0.2.dist-info/RECORD
