Metadata-Version: 2.1
Name: cud
Version: 0.0.2
Summary: A library for cleaning utilities for time-history data
Home-page: https://gitlab.com/davidwoodburn/cud
Author: David Woodburn
Author-email: david.woodburn@icloud.com
Classifier: Programming Language :: Python :: 3
Classifier: License :: OSI Approved :: MIT License
Classifier: Operating System :: OS Independent
Requires-Python: >=3.6
License-File: LICENSE.txt
Requires-Dist: numpy
Requires-Dist: scipy
